taskflowai_ui/__init__.py
taskflowai_ui/chatui.py
taskflowai_ui/formui.py
taskflowai_ui-0.2.0.dist-info/LICENSE
taskflowai_ui-0.2.0.dist-info/METADATA
taskflowai_ui-0.2.0.dist-info/WHEEL
taskflowai_ui-0.2.0.dist-info/RECORD
