Metadata-Version: 2.1
Name: taskflowai_ui
Version: 0.2.0
Summary: UI wrapper for the taskflowai package
License: Apache 2.0
Author: Philippe Andre Page
Author-email: philippeandrepage@gmail.com
Requires-Python: >=3.10,<3.13
Classifier: Development Status :: 4 - Beta
Classifier: Intended Audience :: Developers
Classifier: License :: OSI Approved :: Apache Software License
Classifier: License :: Other/Proprietary License
Classifier: Operating System :: OS Independent
Classifier: Programming Language :: Python :: 3
Classifier: Programming Language :: Python :: 3.10
Classifier: Programming Language :: Python :: 3.11
Classifier: Programming Language :: Python :: 3.12
Requires-Dist: pydantic (>=2.0,<3.0)
Requires-Dist: streamlit (>=1.32.0,<2.0.0)
Requires-Dist: taskflowai (>=0.4.1,<1.0.0)
Project-URL: Bug Tracker, https://github.com/philippeandrepage/taskflowai_ui/issues
Project-URL: Homepage, https://github.com/philippeandrepage/taskflowai_ui
